atqo/__init__.py
atqo/bases.py
atqo/core.py
atqo/distributed_apis.py
atqo/exceptions.py
atqo/exchange.py
atqo/lock_stores.py
atqo/resource_handling.py
atqo/simplified_functions.py
atqo/utils.py
atqo/tests/__init__.py
atqo/tests/test_dist_apis.py
atqo/tests/test_exchange.py
atqo/tests/test_lock_store.py
atqo/tests/test_race.py
atqo/tests/test_resource_handling.py
atqo/tests/test_scheduler.py
atqo/tests/test_scheduler_errors.py
atqo/tests/test_simplified_functions.py
atqo/tests/integration/__init__.py
atqo/tests/integration/test_dn_integration.py
atqo/tests/integration/test_io.py
atqo/tests/integration/test_small_runs.py
atqo-0.4.1.dist-info/LICENSE
atqo-0.4.1.dist-info/WHEEL
atqo-0.4.1.dist-info/METADATA
atqo-0.4.1.dist-info/RECORD
