Metadata-Version: 2.1
Name: atqo
Version: 0.4.1
Summary: Async Task Queue Orchestrator with Complex Resource Management
Author-email: Endre Márk Borza <endremborza@gmail.com>
Requires-Python: >=3.10
Requires-Dist: structlog
Requires-Dist: tblib
Requires-Dist: branthebuilder[doc] ; extra == "doc"
Requires-Dist: tqdm ; extra == "fancy"
Requires-Dist: portalocker ; extra == "fancy"
Requires-Dist: branthebuilder ; extra == "test"
Project-URL: Homepage, https://github.com/endremborza/atqo
Provides-Extra: doc
Provides-Extra: fancy
Provides-Extra: test
